deepreplay/__init__.py
deepreplay/callbacks.py
deepreplay/plot.py
deepreplay/replay.py
deepreplay/utils.py
deepreplay/datasets/__init__.py
deepreplay/datasets/ball.py
deepreplay/datasets/hypercube.py
deepreplay/datasets/parabola.py
deepreplay-0.1.2a2.dist-info/METADATA
deepreplay-0.1.2a2.dist-info/RECORD
deepreplay-0.1.2a2.dist-info/WHEEL
deepreplay-0.1.2a2.dist-info/top_level.txt
examples/__init__.py
examples/circles_dataset.py
examples/comparison_activation_functions.py
examples/moons_dataset.py
examples/part1_activation_functions.py
examples/part2_initializers.py
examples/part2_weight_initializers.py
examples/uci_spambase_dataset.py
