Metadata-Version: 2.1
Name: deepreplay
Version: 0.1.2a2
Summary: "Hyper-parameters in Action!" visualizing tool for Keras models.
Home-page: https://github.com/dvgodoy/deepreplay
Author: Daniel Voigt Godoy
Author-email: datagnosis@gmail.com
License: MIT
Keywords: keras,hyper-parameters,animation,plot,chart
Platform: UNKNOWN
Classifier: Development Status :: 3 - Alpha
Classifier: Intended Audience :: Developers
Classifier: Intended Audience :: Education
Classifier: Intended Audience :: Science/Research
Classifier: Topic :: Scientific/Engineering
Classifier: Topic :: Scientific/Engineering :: Artificial Intelligence
Classifier: Topic :: Scientific/Engineering :: Visualization
Classifier: License :: OSI Approved :: MIT License
Classifier: Programming Language :: Python :: 2
Classifier: Programming Language :: Python :: 3
Requires-Dist: matplotlib
Requires-Dist: numpy
Requires-Dist: h5py
Requires-Dist: seaborn
Requires-Dist: keras
Requires-Dist: scikit-learn
